{
    "$schema": "https://raw.githubusercontent.com/xen-42/outer-wilds-new-horizons/master/NewHorizons/schema.json",
    "name": "Pineapple",
    "starSystem": "tlya.Grapefruit",
    "Base": {
        "hasAmbientLight": true,
        "hasMapMarker": true,
        "surfaceSize": 184,
        "surfaceGravity": 10
    },
    "Orbit": {
        "semiMajorAxis": 13000,
        "primaryBody": "Grapefruit",
        "isTidallyLocked": true,
        "showOrbitLine": true,
        "argumentOfPeriapsis": 125,
        "tint": {"R": 251, "G": 4, "B": 178}
	}
}