<AstroObjectEntry>
    <ID>DRAGONFRUIT</ID>

    <Entry>
        <ID>DRAGONFRUIT_ENTRY</ID>
        <Name>Dragonfruit</Name>

        <Curiosity>GRAPEFRUIT_STAR_SYSTEM_CURIOSITY</Curiosity>

        <RumorFact>
            <ID>DRAGONFRUIT_RUMOR</ID>
            <SourceID>GRAPEFRUIT_ENTRY</SourceID>
            <RumorName>Dragonfruit</RumorName>
            <Text>The second planet from the star.</Text>
        </RumorFact>

        <ExploreFact>
            <ID>DRAGONFRUIT_LANDING</ID>
            <Text>Dragonfruit has air, water, and atmosphere. The most habitable planet in this star system.</Text>
        </ExploreFact>

    </Entry>

    <Entry>
        <ID>DRAGONFRUIT_GEYSERS_ENTRY</ID>
        <Name>Geyser Field</Name>

        <Curiosity>SECRETS_OF_DRAGONFRUIT_CURIOSITY</Curiosity>

        <ExploreFact>
            <ID>DRAGONFRUIT_GEYSERS</ID>
            <Text>Near the north pole of Dragonfruit, I found a field with five geysers.</Text>
        </ExploreFact>

    </Entry>
	
	<Entry>
        <ID>DRAGONFRUIT_RAFT_ENTRY</ID>
        <Name>Raft</Name>

        <Curiosity>SECRETS_OF_DRAGONFRUIT_CURIOSITY</Curiosity>

        <ExploreFact>
            <ID>DRAGONFRUIT_RAFT</ID>
            <Text>I found a raft on the ocean shore. It's very strange, considering there isn't a living soul here. Who built it?</Text>
        </ExploreFact>

    </Entry>
</AstroObjectEntry>